tegdet/__init__.py
tegdet/graph_comparison.py
tegdet/teg.py
tegdet-1.1.0.dist-info/LICENSE
tegdet-1.1.0.dist-info/METADATA
tegdet-1.1.0.dist-info/WHEEL
tegdet-1.1.0.dist-info/top_level.txt
tegdet-1.1.0.dist-info/RECORD
