Metadata-Version: 2.1
Name: tegdet
Version: 1.1.0
Summary: Time Evolving Graph detectors library
Home-page: https://github.com/DiasporeUnizar/TEG
Author: Diaspore team
Author-email: simonab@unizar.es
License: GPL-2
Classifier: Programming Language :: Python
Classifier: Programming Language :: Python :: 3
Classifier: Programming Language :: Python :: 3.6
Classifier: Programming Language :: Python :: 3.7
Classifier: Programming Language :: Python :: 3.8
Classifier: Programming Language :: Python :: 3.9
Classifier: Programming Language :: Python :: 3.10
Classifier: Operating System :: OS Independent
Requires-Python: >=3.6.1
License-File: LICENSE
